{
  "content": {
    "mach-nix": {
      "dependencyTree": {
        "appdirs": [],
        "attrs": [],
        "babel": [
          "pytz"
        ],
        "beautifulsoup4": [
          "soupsieve"
        ],
        "cached-property": [],
        "certifi": [],
        "cffi": [
          "pycparser"
        ],
        "chardet": [],
        "cryptography": [
          "cffi"
        ],
        "decorator": [],
        "defusedxml": [],
        "docutils": [],
        "ebaysdk": [],
        "freezegun": [
          "python-dateutil",
          "six"
        ],
        "gevent": [
          "greenlet",
          "setuptools",
          "zope-event",
          "zope-interface"
        ],
        "greenlet": [],
        "idna": [],
        "isodate": [
          "six"
        ],
        "jinja2": [
          "markupsafe"
        ],
        "libsass": [],
        "lxml": [],
        "markupsafe": [],
        "num2words": [],
        "ofxparse": [],
        "passlib": [],
        "pillow": [],
        "polib": [],
        "psutil": [],
        "psycopg2": [],
        "pyasn1": [],
        "pyasn1-modules": [
          "pyasn1"
        ],
        "pycparser": [],
        "pydot": [
          "pyparsing"
        ],
        "pyopenssl": [
          "cryptography",
          "six"
        ],
        "pyparsing": [],
        "pypdf2": [],
        "pyserial": [],
        "python-dateutil": [
          "six"
        ],
        "python-ldap": [],
        "python-stdnum": [],
        "pytz": [],
        "pyusb": [],
        "qrcode": [
          "six"
        ],
        "reportlab": [
          "pillow"
        ],
        "requests": [
          "certifi",
          "chardet",
          "idna",
          "urllib3"
        ],
        "requests-toolbelt": [
          "requests"
        ],
        "setuptools": [],
        "six": [],
        "soupsieve": [],
        "urllib3": [],
        "vobject": [],
        "werkzeug": [],
        "xlrd": [],
        "xlsxwriter": [],
        "xlwt": [],
        "zeep": [
          "appdirs",
          "attrs",
          "cached-property",
          "defusedxml",
          "isodate",
          "lxml",
          "pytz",
          "requests",
          "requests-toolbelt",
          "six"
        ],
        "zope-event": [
          "setuptools"
        ],
        "zope-interface": [
          "setuptools"
        ]
      },
      "dists": {
        "appdirs": "wheel",
        "attrs": "wheel",
        "babel": "wheel",
        "beautifulsoup4": "wheel",
        "cached-property": "wheel",
        "certifi": "wheel",
        "cffi": "wheel",
        "chardet": "wheel",
        "cryptography": "wheel",
        "decorator": "wheel",
        "defusedxml": "wheel",
        "docutils": "wheel",
        "ebaysdk": "2.1.5",
        "freezegun": "wheel",
        "gevent": "wheel",
        "greenlet": "wheel",
        "idna": "wheel",
        "isodate": "wheel",
        "jinja2": "wheel",
        "libsass": "0.18.0",
        "lxml": "wheel",
        "markupsafe": "1.1.0",
        "num2words": "wheel",
        "ofxparse": "0.19",
        "passlib": "wheel",
        "pillow": "wheel",
        "polib": "wheel",
        "psutil": "5.6.7",
        "psycopg2": "2.8.6",
        "pyasn1": "wheel",
        "pyasn1-modules": "wheel",
        "pycparser": "wheel",
        "pydot": "wheel",
        "pyopenssl": "wheel",
        "pyparsing": "wheel",
        "pypdf2": "1.26.0",
        "pyserial": "wheel",
        "python-dateutil": "wheel",
        "python-ldap": "3.4.0",
        "python-stdnum": "wheel",
        "pytz": "wheel",
        "pyusb": "1.0.2",
        "qrcode": "wheel",
        "reportlab": "wheel",
        "requests": "wheel",
        "requests-toolbelt": "wheel",
        "setuptools": "wheel",
        "six": "wheel",
        "soupsieve": "wheel",
        "urllib3": "wheel",
        "vobject": "0.9.6.1",
        "werkzeug": "wheel",
        "xlrd": "wheel",
        "xlsxwriter": "wheel",
        "xlwt": "wheel",
        "zeep": "wheel",
        "zope-event": "wheel",
        "zope-interface": "wheel"
      }
    }
  },
  "invalidationHash": "cfbfb66cc62670414f09f8cab951abad359f6af8fb2f9e1630e991f4a7f7ec13"
}
